zuken/__init__.py
zuken/devices.py
zuken/e3.py
zuken/sheets.py
zuken/symbols.py
zuken-0.0.3.dist-info/METADATA
zuken-0.0.3.dist-info/WHEEL
zuken-0.0.3.dist-info/licenses/LICENSE
zuken-0.0.3.dist-info/RECORD
