Metadata-Version: 2.1
Name: zuken
Version: 0.0.3
Summary: A small package with functions to help with Zuken (E3) Scripting
Project-URL: Homepage, https://github.com/rory652/Zuken
Project-URL: Issues, https://github.com/rory652/Zuken/issues
Author: Rory
License-File: LICENSE
Classifier: License :: OSI Approved :: GNU General Public License v3 (GPLv3)
Classifier: Operating System :: Microsoft :: Windows
Classifier: Programming Language :: Python :: 3
Requires-Python: >=3.11
